readme_helper/__init__.py
readme_helper/settings.ini
readme_helper-0.0.2.dist-info/LICENSE.txt
readme_helper-0.0.2.dist-info/METADATA
readme_helper-0.0.2.dist-info/WHEEL
readme_helper-0.0.2.dist-info/top_level.txt
readme_helper-0.0.2.dist-info/RECORD
